decimer_segmentation/__init__.py
decimer_segmentation/complete_structure.py
decimer_segmentation/decimer_segmentation.py
decimer_segmentation/optimized_complete_structure.py
decimer_segmentation/mrcnn/config.py
decimer_segmentation/mrcnn/model.py
decimer_segmentation/mrcnn/moldetect.py
decimer_segmentation/mrcnn/utils.py
decimer_segmentation/mrcnn/visualize.py
decimer_segmentation-1.5.0.dist-info/LICENSE
decimer_segmentation-1.5.0.dist-info/METADATA
decimer_segmentation-1.5.0.dist-info/WHEEL
decimer_segmentation-1.5.0.dist-info/top_level.txt
decimer_segmentation-1.5.0.dist-info/RECORD
