Metadata-Version: 2.1
Name: decimer-segmentation
Version: 1.5.0
Summary: DECIMER Segmentation - Extraction of chemical structure depictions from scientific literature
Home-page: https://github.com/Kohulan/DECIMER-Image-Segmentation
Author: Kohulan Rajan
Author-email: kohulan.rajan@uni-jena.de
Maintainer: Kohulan Rajan
Maintainer-email: kohulan.rajan@uni-jena.de
License: MIT
Classifier: Programming Language :: Python :: 3
Classifier: Programming Language :: Python :: 3.10
Classifier: Programming Language :: Python :: 3.11
Classifier: Programming Language :: Python :: 3 :: Only
Classifier: License :: OSI Approved :: MIT License
Classifier: Operating System :: OS Independent
Requires-Python: >=3.10
License-File: LICENSE
Requires-Dist: tensorflow<=2.15.1,>=2.12.0
Requires-Dist: numpy>=1.2.0
Requires-Dist: scikit-image>=0.2.0
Requires-Dist: pillow
Requires-Dist: opencv-python
Requires-Dist: matplotlib
Requires-Dist: IPython
Requires-Dist: PyMuPDF
Requires-Dist: numba
Requires-Dist: scipy
Requires-Dist: requests
